fpsupport/__init__.py
fpsupport/decorator.py
fpsupport/exception.py
fpsupport/file.py
fpsupport/jinja.py
fpsupport/monad.py
fpsupport/struct.py
fpsupport-0.2.0.dist-info/METADATA
fpsupport-0.2.0.dist-info/WHEEL
fpsupport-0.2.0.dist-info/licenses/LICENSE
fpsupport-0.2.0.dist-info/RECORD
