Metadata-Version: 2.4
Name: fpsupport
Version: 0.2.0
Summary: Functional Programming Library and Lessons
License-Expression: Apache-2.0
License-File: LICENSE
Keywords: fp,functional programming,io,monad
Author: George Cummings
Author-email: gmc@cummings-online.ca
Requires-Python: >=3.9
Classifier: Development Status :: 4 - Beta
Classifier: Intended Audience :: Developers
Classifier: Intended Audience :: Education
Classifier: License :: OSI Approved :: Apache Software License
Classifier: Programming Language :: Python :: 3
Classifier: Topic :: Software Development :: Libraries :: Python Modules
Classifier: Topic :: Software Development :: Testing :: Unit
Requires-Dist: jinja2 (>=3.1.6)
Requires-Dist: pydantic (>=2.10.5)
Requires-Dist: pydantic-settings (>=2.8)
Project-URL: Documentation, https://pentheuslennuye.github.io/fpsupport/
Project-URL: Homepage, https://pentheuslennuye.github.io/fpsupport/
Project-URL: Repository, https://github.com/PentheusLennuye/fpsupport.git
Project-URL: changelog, https://github.com/PentheusLennuye/fpsupport/blob/master/CHANGELOG.md
Project-URL: issues, https://github.com/PentheusLennuye/fpsupport/issues
